setup.cfg
setup.py
better_od/__init__.py
better_od/__main__.py
better_od/core.py
better_od.egg-info/PKG-INFO
better_od.egg-info/SOURCES.txt
better_od.egg-info/dependency_links.txt
better_od.egg-info/not-zip-safe
better_od.egg-info/top_level.txt
tests/__init__.py
tests/main.py