Metadata-Version: 1.0
Name: better-od
Version: 0.2.1
Summary: A more flexible implementation of OrderedDict
Home-page: https://github.com/therealfakemoot/BetterOrderedDict/
Author: Nick Dumas
Author-email: drakonik@gmail.com
License: UNKNOWN
Platform: UNKNOWN
